sec_cik_mapper/BaseMapper.py
sec_cik_mapper/MutualFundMapper.py
sec_cik_mapper/StockMapper.py
sec_cik_mapper/__init__.py
sec_cik_mapper/_version.py
sec_cik_mapper/py.typed
sec_cik_mapper/retrievers.py
sec_cik_mapper/types.py
sec_cik_mapper/utils.py
sec_cik_mapper-2.1.0.dist-info/LICENSE
sec_cik_mapper-2.1.0.dist-info/WHEEL
sec_cik_mapper-2.1.0.dist-info/METADATA
sec_cik_mapper-2.1.0.dist-info/RECORD
