Metadata-Version: 2.1
Name: sec-cik-mapper
Version: 2.1.0
Summary: Generate mappings between SEC identifiers using Python
Keywords: sec,edgar,filing,financial,finance,stocks,mutual funds,etfs,cik,ticker
Author-email: Jad Chaar <jad.chaar@gmail.com>
Requires-Python: >=3.6
Classifier: Development Status :: 5 - Production/Stable
Classifier: Intended Audience :: Developers
Classifier: Intended Audience :: Information Technology
Classifier: Intended Audience :: Financial and Insurance Industry
Classifier: Natural Language :: English
Classifier: Topic :: Software Development :: Libraries :: Python Modules
Classifier: Topic :: Office/Business :: Financial
Classifier: Topic :: Office/Business :: Financial :: Investment
Classifier: License :: OSI Approved :: MIT License
Classifier: Programming Language :: Python :: 3
Classifier: Programming Language :: Python :: 3.6
Classifier: Programming Language :: Python :: 3.7
Classifier: Programming Language :: Python :: 3.8
Classifier: Programming Language :: Python :: 3.9
Classifier: Programming Language :: Python :: 3.10
Classifier: Programming Language :: Python :: 3 :: Only
Classifier: Operating System :: OS Independent
Requires-Dist: requests
Requires-Dist: pandas
Requires-Dist: typing_extensions
Requires-Dist: sphinx ; extra == "doc"
Requires-Dist: sphinx-autodoc-typehints ; extra == "doc"
Requires-Dist: pytest ; extra == "test"
Requires-Dist: pytest-cov ; extra == "test"
Project-URL: Documentation, https://sec-cik-mapper.readthedocs.io
Project-URL: Issues, https://github.com/jadchaar/cik-mapper/issues
Project-URL: Source, https://github.com/jadchaar/cik-mapper
Provides-Extra: doc
Provides-Extra: test
